LICENSE.txt
MANIFEST.in
README.rst
requirements.txt
setup.cfg
setup.py
docs/Makefile
docs/api.rst
docs/conf.py
docs/discuss.rst
docs/favicon.png
docs/guides.rst
docs/index.rst
docs/make.bat
docs/onboarding.rst
docs/requirements.txt
docs/api/angles.rst
docs/api/builtin.rst
docs/api/colors.rst
docs/api/decoders.rst
docs/api/errors.rst
docs/discuss/color-expressions.rst
docs/discuss/colors.rst
docs/guides/defining-decoders.rst
docs/onboarding/installing.rst
docs/onboarding/trying.rst
thcolor/__init__.py
thcolor/angles.py
thcolor/builtin.py
thcolor/colors.py
thcolor/decoders.py
thcolor/errors.py
thcolor/utils.py
thcolor/version.py
thcolor.egg-info/PKG-INFO
thcolor.egg-info/SOURCES.txt
thcolor.egg-info/dependency_links.txt
thcolor.egg-info/not-zip-safe
thcolor.egg-info/top_level.txt