Metadata-Version: 2.1
Name: thcolor
Version: 0.4
Summary: color management module
Home-page: https://thcolor.touhey.pro/
Author: Thomas Touhey
Author-email: thomas@touhey.fr
License: MIT
Project-URL: Documentation, https://thcolor.touhey.pro/docs/
Keywords: textout,color,parser,css
Platform: UNKNOWN
Classifier: Development Status :: 4 - Beta
Classifier: Natural Language :: English
Classifier: License :: OSI Approved :: MIT License
Classifier: Operating System :: OS Independent
Classifier: Programming Language :: Python :: 3
Classifier: Intended Audience :: Developers
Classifier: Topic :: Text Processing :: Markup :: HTML
Requires-Python: >=3.6
License-File: LICENSE.txt
